[{"nodeType":"BACKGROUND","nodeId":0,"nodeZIndex":0},{"nodeType":"CONNECTABLE","nodeId":34,"nodeZIndex":210,"nodeSettings":{"color":"#C0C0C0","rect":{"y1":32,"x1":32,"y2":160,"x2":160},"name":"HeatmapRegressionDatagen"},"srcConnIdList":[40],"dstConnIdList":[],"nodeParams":{"type":"NONE_ANY","blockType":"HEATMAP_REGRESSION_DATAGEN","params":{"dataset_name":"faceali128x128","train_procedure":"HEATMAP_REGRESSION","image_shape":[112,112,1],"total_train_examples":1000,"total_test_examples":200,"batch_size":100,"epochs":100}}},{"nodeType":"CONNECTABLE","nodeId":35,"nodeZIndex":220,"nodeSettings":{"color":"#004000","rect":{"y1":32,"x1":176,"y2":160,"x2":304},"name":"InputLayer"},"srcConnIdList":[41],"dstConnIdList":[40],"nodeParams":{"type":"ONE_ANY","blockType":"INPUT_LAYER","params":{"batch_size":100,"input_shape":[112,112,1],"dtype":"float32","shape":[112,112,3]}}},{"nodeType":"CONNECTABLE","nodeId":36,"nodeZIndex":230,"nodeSettings":{"color":"#00E080","rect":{"y1":32,"x1":320,"y2":160,"x2":448},"name":"Conv2DBlock"},"srcConnIdList":[42],"dstConnIdList":[41],"nodeParams":{"type":"ONE_ANY","blockType":"CONV2D_BLOCK","params":{"name":"CONV2D_BLOCK0","filters":16,"kernel_size":[3,3],"strides":[1,1],"padding":"same","use_bias":1,"trainable":1,"bn_trainable":1,"activation":"relu"}}},{"nodeType":"CONNECTABLE","nodeId":37,"nodeZIndex":240,"nodeSettings":{"color":"#F04040","rect":{"y1":32,"x1":464,"y2":160,"x2":592},"name":"HourglassBlock"},"srcConnIdList":[43],"dstConnIdList":[42],"nodeParams":{"type":"ONE_ANY","blockType":"HOURGLASS_BLOCK","params":{"name":"HOURGLASS_BLOCK0","depth":4,"use_bias":1,"trainable":1,"bn_trainable":1,"repeat":2}}},{"nodeType":"CONNECTABLE","nodeId":38,"nodeZIndex":250,"nodeSettings":{"color":"#00E080","rect":{"y1":32,"x1":608,"y2":160,"x2":736},"name":"Conv2DBlock"},"srcConnIdList":[44],"dstConnIdList":[43],"nodeParams":{"type":"ONE_ANY","blockType":"CONV2D_BLOCK","params":{"name":"CONV2D_BLOCK1","filters":5,"kernel_size":[3,3],"strides":[1,1],"padding":"same","use_bias":1,"trainable":1,"bn_trainable":1,"activation":"relu"}}},{"nodeType":"CONNECTABLE","nodeId":39,"nodeZIndex":260,"nodeSettings":{"color":"#C0C0C0","rect":{"y1":32,"x1":752,"y2":160,"x2":880},"name":"HMRLossFunc"},"srcConnIdList":[],"dstConnIdList":[44],"nodeParams":{"type":"ONE_NONE","blockType":"LOSS_FUNC_HMR","params":{"name":"HeatmapRegression"}}},{"nodeType":"CONNECTION","nodeId":40,"nodeZIndex":1000000,"srcPosition":{"y":96,"x":96},"dstPosition":{"y":96,"x":240},"srcNodeId":34,"dstNodeId":35},{"nodeType":"CONNECTION","nodeId":41,"nodeZIndex":1000010,"srcPosition":{"y":96,"x":240},"dstPosition":{"y":96,"x":384},"srcNodeId":35,"dstNodeId":36},{"nodeType":"CONNECTION","nodeId":42,"nodeZIndex":1000020,"srcPosition":{"y":96,"x":384},"dstPosition":{"y":96,"x":528},"srcNodeId":36,"dstNodeId":37},{"nodeType":"CONNECTION","nodeId":43,"nodeZIndex":1000030,"srcPosition":{"y":96,"x":528},"dstPosition":{"y":96,"x":672},"srcNodeId":37,"dstNodeId":38},{"nodeType":"CONNECTION","nodeId":44,"nodeZIndex":1000040,"srcPosition":{"y":96,"x":672},"dstPosition":{"y":96,"x":816},"srcNodeId":38,"dstNodeId":39}]